<?xml version="1.0" encoding="utf-8" ?><dwsync><file name="index.html" server="ftp.afms.org.au" local="3814560253" remote="3814560240" Dst="-1" /><file name="dates.html" server="ftp.afms.org.au" local="3814560299" remote="3814560240" Dst="-1" /><file name="accommodation.html" server="ftp.afms.org.au" local="3814574368" remote="3814574340" Dst="-1" /><file name="aboutCanberra.html" server="ftp.afms.org.au" local="3814574409" remote="3814574400" Dst="-1" /><file name="venue.html" server="ftp.afms.org.au" local="3814557666" remote="3814557660" Dst="-1" /><file name="abstracts.html" server="ftp.afms.org.au" local="3814574389" remote="3814574340" Dst="-1" /><file name="committees.html" server="ftp.afms.org.au" local="3814574241" remote="3814574220" Dst="-1" /><file name="keynotes.html" server="ftp.afms.org.au" local="3814559982" remote="3814559940" Dst="-1" /><file name="sponsors.html" server="ftp.afms.org.au" local="3814574093" remote="3814574040" Dst="-1" /><file name="prizes.html" server="ftp.afms.org.au" local="3814559658" remote="3814559640" Dst="-1" /><file name="visas.html" server="ftp.afms.org.au" local="3814557830" remote="3814557780" Dst="-1" /><file name="ecrmcr.html" server="ftp.afms.org.au" local="3814560336" remote="3814560300" Dst="-1" /><file name="registration.html" server="ftp.afms.org.au" local="3814557936" remote="3814557900" Dst="-1" /><file name="program.html" server="ftp.afms.org.au" local="3814578430" remote="3814578420" Dst="-1" /><file name="posters.html" server="ftp.afms.org.au" local="3814559718" remote="3814559700" Dst="-1" /><file name="hdr.html" server="ftp.afms.org.au" local="3814560268" remote="3814560240" Dst="-1" /><file name="wifm.html" server="ftp.afms.org.au" local="3814557061" remote="3814557060" Dst="-1" /><file name="tours.html" server="ftp.afms.org.au" local="3814577995" remote="3814577940" Dst="-1" /></dwsync>